LICENSE.txt
MANIFEST.in
README.md
setup.py
mkauthdocs/__init__.py
mkauthdocs/__main__.py
mkauthdocs.egg-info/PKG-INFO
mkauthdocs.egg-info/SOURCES.txt
mkauthdocs.egg-info/dependency_links.txt
mkauthdocs.egg-info/entry_points.txt
mkauthdocs.egg-info/top_level.txt
mkauthdocs/templates/login_template.php
mkauthdocs/templates/session_guard_template.php