Metadata-Version: 2.1
Name: mkauthdocs
Version: 0.1.7
Summary: An authentication tool for mkdocs builds
Home-page: https://github.com/ctxz/mkauthdocs
Author: Patrick Pedersen
Author-email: ctx.xda@gmail.com
License: UNKNOWN
Project-URL: Mkdocs, http://www.mkdocs.org/
Project-URL: Bug Reports, https://github.com/ctxz/mkauthdocs/issues
Project-URL: Source, https://github.com/ctxz/mkauthdocs/
Keywords: mkdocs authentication documentation
Platform: UNKNOWN
Classifier: Development Status :: 4 - Beta
Classifier: Intended Audience :: Developers
Classifier: Topic :: Software Development :: Documentation
Classifier: License :: OSI Approved :: MIT License
Classifier: Programming Language :: Python :: 2
Classifier: Programming Language :: Python :: 2.7
Classifier: Programming Language :: Python :: 3
Classifier: Programming Language :: Python :: 3.4
Classifier: Programming Language :: Python :: 3.5
Classifier: Programming Language :: Python :: 3.6
License-File: LICENSE.txt
